{
    "prof_info": [
        {
            "prof_name": "Jonathan Barbour",
            "prof_id": 2518,
            "total_reviews": 1
        }
    ],
    "reviews": [
        {
            "course_name": "Planet Earth Spring 2005",
            "review_date": "May 08, 2005",
            "review_content": "\nJonathan is one of the best TAs at Columbia.  He was always available, and his knowledge of the subject was spot on.  He's a fair grader and worked well with Prof. Anderson.   \nWorkload:\nWeekly Quizzes, Weekly Group Projects (Cool social environment for meeting other students!) Midterm and non-cumulative Final Exam.\n"
        }
    ]
}